{
    "phoneTypes": [
        {
            "type": 1,
            "name": "Iphone XS"
        },
        {
            "type": 2,
            "name": "Iphone 12 / 12 pro"
        },
        {
            "type": 3,
            "name": "Iphone 12 Pro Max"
        },
        {
            "type": 4,
            "name": "Iphone 12 mini"
        },
        {
            "type": 5,
            "name": "Iphone X"
        },
        {
            "type": 6,
            "name": "Iphone XR"
        },
        {
            "type": 7, 
            "name": "Samsung s20"
        }
    ]
}